LICENSE
MANIFEST.in
README.md
requirements.txt
setup.cfg
setup.py
cocaine/__init__.py
cocaine/proxy/__init__.py
cocaine/proxy/helpers.py
cocaine/proxy/jsonrpc.py
cocaine/proxy/logutils.py
cocaine/proxy/mds_direct.py
cocaine/proxy/mds_exec.py
cocaine/proxy/plugin.py
cocaine/proxy/proxy.py
cocaine/proxy/utilserver.py
cocaine/tools/__init__.py
cocaine/tools/cli.py
cocaine/tools/cocaine_tool.py
cocaine/tools/dispatch.py
cocaine/tools/error.py
cocaine/tools/installer.py
cocaine/tools/printer.py
cocaine/tools/repository.py
cocaine/tools/tags.py
cocaine/tools/version.py
cocaine/tools/actions/__init__.py
cocaine/tools/actions/app.py
cocaine/tools/actions/auth.py
cocaine/tools/actions/common.py
cocaine/tools/actions/crashlog.py
cocaine/tools/actions/docker.py
cocaine/tools/actions/group.py
cocaine/tools/actions/keyring.py
cocaine/tools/actions/logs.py
cocaine/tools/actions/profile.py
cocaine/tools/actions/proxy.py
cocaine/tools/actions/runlist.py
cocaine/tools/actions/timeouts.py
cocaine/tools/actions/tracing.py
cocaine/tools/actions/access/__init__.py
cocaine/tools/actions/access/event.py
cocaine/tools/actions/access/storage.py
cocaine/tools/actions/mql/__init__.py
cocaine/tools/helpers/__init__.py
cocaine/tools/helpers/_unix.py
cocaine/tools/helpers/completer.py
cocaine/tools/helpers/dockertemplate.py
cocaine/tools/helpers/editor.py
cocaine/tools/interactive/__init__.py
cocaine/tools/plugins/__init__.py
cocaine/tools/plugins/secure/__init__.py
cocaine/tools/plugins/secure/promiscuous.py
cocaine/tools/plugins/secure/tvm.py
cocaine_tools.egg-info/PKG-INFO
cocaine_tools.egg-info/SOURCES.txt
cocaine_tools.egg-info/dependency_links.txt
cocaine_tools.egg-info/entry_points.txt
cocaine_tools.egg-info/namespace_packages.txt
cocaine_tools.egg-info/not-zip-safe
cocaine_tools.egg-info/requires.txt
cocaine_tools.egg-info/top_level.txt
tests/requirements.txt