Metadata-Version: 1.1
Name: cocaine-tools
Version: 0.12.13.4
Summary: Cocaine Tools for Cocaine Application Cloud.
Home-page: https://github.com/cocaine/cocaine-tools
Author: Evgeny Safronov
Author-email: division494@gmail.com
License: LGPLv3+
Platform: Linux
Platform: BSD
Platform: MacOS
Classifier: Programming Language :: Python
Classifier: Programming Language :: Python :: 2.7
Classifier: Programming Language :: Python :: 3.4
Classifier: Programming Language :: Python :: Implementation :: CPython
Classifier: Development Status :: 4 - Beta
